orcapod_sanctuary/__init__.py
orcapod_sanctuary-0.0.1.dist-info/METADATA
orcapod_sanctuary-0.0.1.dist-info/WHEEL
orcapod_sanctuary-0.0.1.dist-info/top_level.txt
orcapod_sanctuary-0.0.1.dist-info/RECORD
