Metadata-Version: 2.4
Name: orcapod-sanctuary
Version: 0.0.1
Summary: Archival of past orcapod context implementations for backward compatibility
Requires-Python: >=3.13
